japaneseverbconjugator/__init__.py
japaneseverbconjugator/private/NegativeVerbFormGenerator.py
japaneseverbconjugator/private/PositiveVerbFormGenerator.py
japaneseverbconjugator/private/Utils.py
japaneseverbconjugator/private/__init__.py
japaneseverbconjugator/src/Decorators.py
japaneseverbconjugator/src/JapaneseVerbFormGenerator.py
japaneseverbconjugator/src/NegativeVerbFormGenerator.py
japaneseverbconjugator/src/PositiveVerbFormGenerator.py
japaneseverbconjugator/src/Utils.py
japaneseverbconjugator/src/__init__.py
japaneseverbconjugator/src/driver.py
japaneseverbconjugator/src/constants/EnumeratedTypes.py
japaneseverbconjugator/src/constants/ParticleConstants.py
japaneseverbconjugator/src/constants/VerbEndingConstants.py
japaneseverbconjugator/src/constants/__init__.py
japaneseverbconjugator/test/DecoratorsTests.py
japaneseverbconjugator/test/JapaneseVerbFormGeneratorTests.py
japaneseverbconjugator/test/TestConstants.py
japaneseverbconjugator/test/UtilsTests.py
japaneseverbconjugator/test/__init__.py
JapaneseVerbConjugator-1.0.1.dist-info/LICENSE.txt
JapaneseVerbConjugator-1.0.1.dist-info/METADATA
JapaneseVerbConjugator-1.0.1.dist-info/WHEEL
JapaneseVerbConjugator-1.0.1.dist-info/top_level.txt
JapaneseVerbConjugator-1.0.1.dist-info/RECORD
