Metadata-Version: 2.1
Name: JapaneseVerbConjugator
Version: 1.0.1
Summary: Japanese verb Conjugator
Home-page: https://github.com/jShiohaha/JapaneseVerbConjugator/
Author: Jacob Shiohira
Author-email: shiohira.jacob@gmail.com
License: UNKNOWN
Platform: UNKNOWN
Classifier: Programming Language :: Python :: 3
Classifier: License :: OSI Approved :: BSD License
Requires-Dist: romkan
